odoo/addons/partner_ref_unique/README.rst
odoo/addons/partner_ref_unique/__init__.py
odoo/addons/partner_ref_unique/__manifest__.py
odoo/addons/partner_ref_unique/i18n/am.po
odoo/addons/partner_ref_unique/i18n/ar.po
odoo/addons/partner_ref_unique/i18n/bg.po
odoo/addons/partner_ref_unique/i18n/bs.po
odoo/addons/partner_ref_unique/i18n/ca.po
odoo/addons/partner_ref_unique/i18n/cs.po
odoo/addons/partner_ref_unique/i18n/da.po
odoo/addons/partner_ref_unique/i18n/de.po
odoo/addons/partner_ref_unique/i18n/el_GR.po
odoo/addons/partner_ref_unique/i18n/en_GB.po
odoo/addons/partner_ref_unique/i18n/es.po
odoo/addons/partner_ref_unique/i18n/es_CR.po
odoo/addons/partner_ref_unique/i18n/es_EC.po
odoo/addons/partner_ref_unique/i18n/es_ES.po
odoo/addons/partner_ref_unique/i18n/es_MX.po
odoo/addons/partner_ref_unique/i18n/es_VE.po
odoo/addons/partner_ref_unique/i18n/et.po
odoo/addons/partner_ref_unique/i18n/eu.po
odoo/addons/partner_ref_unique/i18n/fi.po
odoo/addons/partner_ref_unique/i18n/fr.po
odoo/addons/partner_ref_unique/i18n/fr_CA.po
odoo/addons/partner_ref_unique/i18n/fr_CH.po
odoo/addons/partner_ref_unique/i18n/fr_FR.po
odoo/addons/partner_ref_unique/i18n/gl.po
odoo/addons/partner_ref_unique/i18n/hr.po
odoo/addons/partner_ref_unique/i18n/hr_HR.po
odoo/addons/partner_ref_unique/i18n/hu.po
odoo/addons/partner_ref_unique/i18n/it.po
odoo/addons/partner_ref_unique/i18n/ja.po
odoo/addons/partner_ref_unique/i18n/lt.po
odoo/addons/partner_ref_unique/i18n/lv.po
odoo/addons/partner_ref_unique/i18n/mk.po
odoo/addons/partner_ref_unique/i18n/mn.po
odoo/addons/partner_ref_unique/i18n/nb.po
odoo/addons/partner_ref_unique/i18n/nb_NO.po
odoo/addons/partner_ref_unique/i18n/nl.po
odoo/addons/partner_ref_unique/i18n/nl_BE.po
odoo/addons/partner_ref_unique/i18n/nl_NL.po
odoo/addons/partner_ref_unique/i18n/partner_ref_unique.pot
odoo/addons/partner_ref_unique/i18n/pl.po
odoo/addons/partner_ref_unique/i18n/pt.po
odoo/addons/partner_ref_unique/i18n/pt_BR.po
odoo14_addon_partner_ref_unique-14.0.1.0.1.dev9.dist-info/METADATA
odoo14_addon_partner_ref_unique-14.0.1.0.1.dev9.dist-info/WHEEL
odoo14_addon_partner_ref_unique-14.0.1.0.1.dev9.dist-info/top_level.txt
odoo14_addon_partner_ref_unique-14.0.1.0.1.dev9.dist-info/RECORD
